loci_api/__init__.py
loci_api/__main__.py
loci_api/api_helper.py
loci_api-0.2.33.data/scripts/loci_api
loci_api-0.2.33.dist-info/METADATA
loci_api-0.2.33.dist-info/WHEEL
loci_api-0.2.33.dist-info/top_level.txt
loci_api-0.2.33.dist-info/RECORD
